CryptoMathTrade/exchange/__init__.py
CryptoMathTrade/exchange/_api.py
CryptoMathTrade/exchange/_core.py
CryptoMathTrade/exchange/_request.py
CryptoMathTrade/exchange/_response.py
CryptoMathTrade/exchange/ascendex/__init__.py
CryptoMathTrade/exchange/ascendex/_urls.py
CryptoMathTrade/exchange/ascendex/core.py
CryptoMathTrade/exchange/binance/__init__.py
CryptoMathTrade/exchange/binance/_account.py
CryptoMathTrade/exchange/binance/_api.py
CryptoMathTrade/exchange/binance/_market.py
CryptoMathTrade/exchange/binance/_serialization.py
CryptoMathTrade/exchange/binance/_spot.py
CryptoMathTrade/exchange/binance/_urls.py
CryptoMathTrade/exchange/binance/core.py
CryptoMathTrade/exchange/bingx/__init__.py
CryptoMathTrade/exchange/bingx/_account.py
CryptoMathTrade/exchange/bingx/_api.py
CryptoMathTrade/exchange/bingx/_market.py
CryptoMathTrade/exchange/bingx/_serialization.py
CryptoMathTrade/exchange/bingx/_spot.py
CryptoMathTrade/exchange/bingx/_urls.py
CryptoMathTrade/exchange/bingx/core.py
CryptoMathTrade/exchange/bitget/__init__.py
CryptoMathTrade/exchange/bitget/_api.py
CryptoMathTrade/exchange/bitget/_market.py
CryptoMathTrade/exchange/bitget/_serialization.py
CryptoMathTrade/exchange/bitget/_urls.py
CryptoMathTrade/exchange/bitget/core.py
CryptoMathTrade/exchange/bitmart/__init__.py
CryptoMathTrade/exchange/bitmart/_api.py
CryptoMathTrade/exchange/bitmart/_market.py
CryptoMathTrade/exchange/bitmart/_serialization.py
CryptoMathTrade/exchange/bitmart/_urls.py
CryptoMathTrade/exchange/bitmart/core.py
CryptoMathTrade/exchange/errors.py
CryptoMathTrade/exchange/gate/__init__.py
CryptoMathTrade/exchange/gate/_api.py
CryptoMathTrade/exchange/gate/_market.py
CryptoMathTrade/exchange/gate/_serialization.py
CryptoMathTrade/exchange/gate/_urls.py
CryptoMathTrade/exchange/gate/core.py
CryptoMathTrade/exchange/htx/__init__.py
CryptoMathTrade/exchange/htx/_api.py
CryptoMathTrade/exchange/htx/_market.py
CryptoMathTrade/exchange/htx/_serialization.py
cryptomathtrade-0.7.0.dist-info/entry_points.txt
cryptomathtrade-0.7.0.dist-info/METADATA
cryptomathtrade-0.7.0.dist-info/WHEEL
cryptomathtrade-0.7.0.dist-info/RECORD
